{
  "username": "bngjeck992",
  "album": [
    "PlaneWingWallpaper"
  ],
  "init_jumlah_photo": 100,
  "pub_id": "pub-9601865255535750",
  "app_id": "ca-app-pub-6673662992108923~3577510052",
  "admob_banner_id": "ca-app-pub-6673662992108923/2264428386",
  "admob_interstitial_id": "ca-app-pub-6673662992108923/8638265043",
  "admob_native_id": "ca-app-pub-6673662992108923/4699020032",

  "admob_hpk_1": "Insurance",
  "admob_hpk_2": "Gas/Electricity",
  "admob_hpk_3": "Loans",
  "admob_hpk_4": "Mortgage",
  "admob_hpk_5": "Degree",

  "fan_banner_id": "",
  "fan_interstitial_id": "",
  "fan_native_id": "",

  "startapp_app_id": "21077",

  "unity_id": "",
  "unity_banner": "",
  "unity_interstitial": "",

  "interstitial_inverval": 10,

  "list_ads": [
    "ADMOB",
    "UNITY",
    "STARTAPP",
    "FAN"
  ]
}
